hdx/api/__init__.py
hdx/api/_version.py
hdx/api/configuration.py
hdx/api/hdx_base_configuration.yaml
hdx/api/locations.py
hdx/api/remotehdx.py
hdx/api/utilities/__init__.py
hdx/api/utilities/dataset_title_helper.py
hdx/api/utilities/date_helper.py
hdx/api/utilities/filestore_helper.py
hdx/api/utilities/hdx_error_handler.py
hdx/api/utilities/hdx_state.py
hdx/data/__init__.py
hdx/data/dataset.py
hdx/data/hdx_datasource_topline.yaml
hdx/data/hdxobject.py
hdx/data/indicator_resource_view_template.yaml
hdx/data/organization.py
hdx/data/resource.py
hdx/data/resource_matcher.py
hdx/data/resource_view.py
hdx/data/showcase.py
hdx/data/user.py
hdx/data/vocabulary.py
hdx/facades/__init__.py
hdx/facades/infer_arguments.py
hdx/facades/keyword_arguments.py
hdx/facades/simple.py
hdx_python_api-6.6.1.dist-info/METADATA
hdx_python_api-6.6.1.dist-info/WHEEL
hdx_python_api-6.6.1.dist-info/licenses/LICENSE
hdx_python_api-6.6.1.dist-info/RECORD
