Metadata-Version: 2.4
Name: hdx-python-api
Version: 6.6.1
Summary: HDX Python API for interacting with the Humanitarian Data Exchange
Project-URL: Homepage, https://github.com/OCHA-DAP/hdx-python-api
Author: Michael Rans
License: MIT
License-File: LICENSE
Keywords: API,CKAN,HDX,humanitarian data exchange
Classifier: Development Status :: 5 - Production/Stable
Classifier: Intended Audience :: Developers
Classifier: License :: OSI Approved :: MIT License
Classifier: Natural Language :: English
Classifier: Operating System :: MacOS
Classifier: Operating System :: Microsoft :: Windows
Classifier: Operating System :: POSIX :: Linux
Classifier: Operating System :: Unix
Classifier: Programming Language :: Python
Classifier: Programming Language :: Python :: 3
Classifier: Programming Language :: Python :: 3 :: Only
Classifier: Programming Language :: Python :: 3.8
Classifier: Programming Language :: Python :: 3.9
Classifier: Programming Language :: Python :: 3.10
Classifier: Programming Language :: Python :: 3.11
Classifier: Programming Language :: Python :: 3.12
Classifier: Topic :: Software Development :: Libraries :: Python Modules
Requires-Python: >=3.10
Requires-Dist: ckanapi>=4.8
Requires-Dist: defopt>=7.0.0
Requires-Dist: email-validator
Requires-Dist: hdx-python-country>=4.0.1
Requires-Dist: hdx-python-utilities>=4.0.2
Requires-Dist: libhxl>=5.2.2
Requires-Dist: makefun
Requires-Dist: quantulum3
Requires-Dist: requests
Provides-Extra: dev
Requires-Dist: pre-commit; extra == 'dev'
Provides-Extra: docs
Requires-Dist: mkapi; extra == 'docs'
Provides-Extra: test
Requires-Dist: gspread; extra == 'test'
Requires-Dist: pytest; extra == 'test'
Requires-Dist: pytest-check; extra == 'test'
Requires-Dist: pytest-cov; extra == 'test'
